Workbook

Sheet Cover
A1: At-home beauty trial: unit economics model
A3: Question | B3: Does an at-home, advisor-led try-and-buy visit make money, and which levers matter most?
A4: Approach | B4: Per-visit P&L (revenue, gross profit, advisor, travel, testers, shrinkage) → contribution per visit, break-even visits per advisor per day, then per-customer economics including app reorders and CAC payback.
A5: Selected scenario | B5: =Inputs!B22 -> Base
A6: Contribution per visit | B6: =INDEX(Model!B8:D8,1,Inputs!B23-1) -> 43
A7: Break-even visits per advisor per day | B7: =INDEX(Model!B10:D10,1,Inputs!B23-1) -> 3.5885167
A8: CAC payback (months) | B8: =INDEX(Model!B13:D13,1,Inputs!B23-1) -> 6.9808028
A9: Share of yearly contribution from app reorders | B9: =INDEX(Model!B12:D12,1,Inputs!B23-1) -> 0.92495637
A10: Colour code | B10: Blue on yellow = assumption to change; black = formula.
A11: Important | B11: All inputs are illustrative assumptions, not Wingit data.

Sheet Inputs
A1: Inputs: illustrative assumptions (blue on yellow). Replace with real data.
A3: Assumption | B3: Bear | C3: Base | D3: Bull | E3: Unit | F3: Basis
A4: Products tried per visit | B4: 12 | C4: 15 | D4: 18 | E4: items | F4: Kit of 12-18 items, in line with the pre-visit profile PRD
A5: Visit conversion (customer buys at least one item) | B5: 0.45 | C5: 0.6 | D5: 0.75 | E5: % | F5: Assumption: try-before-you-pay should convert far above online browsing
A6: Items bought per converting visit | B6: 1.5 | C6: 2.2 | D6: 3 | E6: items | F6: Assumption
A7: Average selling price per item | B7: 1800 | C7: 2500 | D7: 3200 | E7: ₹ | F7: Assumption for premium makeup, skincare and fragrance
A8: Gross margin on products | B8: 0.25 | C8: 0.3 | D8: 0.35 | E8: % | F8: Assumption: retailer margin on premium beauty
A9: Discounts and payment costs | B9: 0.06 | C9: 0.04 | D9: 0.03 | E9: % of revenue | F9: Assumption
A10: Advisor cost per working day | B10: 1600 | C10: 1500 | D10: 1400 | E10: ₹/day | F10: Assumption: salary + incentives / working days
A11: Visits per advisor per day | B11: 3 | C11: 4 | D11: 5 | E11: visits | F11: Assumption: travel between homes limits visits
A12: Travel cost per visit | B12: 250 | C12: 200 | D12: 160 | E12: ₹ | F12: Assumption: two-wheeler/cab within a city cluster
A13: Testers and consumables per visit | B13: 220 | C13: 180 | D13: 150 | E13: ₹ | F13: Assumption: hygienic single-use testers
A14: Shrinkage / damage per visit | B14: 80 | C14: 60 | D14: 40 | E14: ₹ | F14: Assumption
A15: CAC per new customer (first visit booked) | B15: 1500 | C15: 1000 | D15: 700 | E15: ₹ | F15: Assumption: premium targeting via Instagram and referrals
... A19: Fulfilment cost per app reorder | B19: 150 | C19: 120 | D19: 100 | E19: ₹ | F19: Assumption: courier/quick delivery
A22: Selected scenario (type Bear, Base or Bull) | B22: Base
A23: Scenario column (2 = Bear, 3 = Base, 4 = Bull) | B23: =MATCH(B22,{"Bear","Base","Bull"},0)+1 -> 3
A25: Every number here is an illustrative assumption (Wingit's real figures are not public). The model shows how the economics work and which levers matter; replace inputs with real data.

Sheet Model
A1: Unit economics by scenario (all formulas)
A3: Line | B3: Bear | C3: Base | D3: Bull | E3: How it's calculated
A4: Revenue per visit | B4: =Inputs!$B$5*Inputs!$B$6*Inputs!$B$7 -> 1215 | C4: =Inputs!$C$5*Inputs!$C$6*Inputs!$C$7 -> 3300 | D4: =Inputs!$D$5*Inputs!$D$6*Inputs!$D$7 -> 7200 | E4: conversion × items per converting visit × price
A5: Gross profit per visit | B5: =B4*(Inputs!$B$8-Inputs!$B$9) -> 230.85 | C5: =C4*(Inputs!$C$8-Inputs!$C$9) -> 858 | D5: =D4*(Inputs!$D$8-Inputs!$D$9) -> 2304 | E5: revenue × (margin − discounts and payment costs)
A6: Advisor cost per visit | B6: =Inputs!$B$10/Inputs!$B$11 -> 533.33333 | C6: =Inputs!$C$10/Inputs!$C$11 -> 375 | D6: =Inputs!$D$10/Inputs!$D$11 -> 280 | E6: daily advisor cost ÷ visits per day
A7: Travel, testers and shrinkage per visit | B7: =Inputs!$B$12+Inputs!$B$13+Inputs!$B$14 -> 550 | C7: =Inputs!$C$12+Inputs!$C$13+Inputs!$C$14 -> 440 | D7: =Inputs!$D$12+Inputs!$D$13+Inputs!$D$14 -> 350 | E7: sum of per-visit variable costs
A8: Contribution per visit | B8: =B5-B6-B7 -> -852.48333 | C8: =C5-C6-C7 -> 43 | D8: =D5-D6-D7 -> 1674 | E8: gross profit − advisor − other variable costs
A9: Contribution margin per visit | B9: =IF(B4=0,0,B8/B4) -> -0.70163237 | C9: =IF(C4=0,0,C8/C4) -> 0.013030303 | D9: =IF(D4=0,0,D8/D4) -> 0.2325 | E9: contribution ÷ revenue
A10: Break-even visits per advisor per day | B10: =IF((B5-B7)<=0,"never",Inputs!$B$10/(B5-B7)) -> never | C10: =IF((C5-C7)<=0,"never",Inputs!$C$10/(C5-C7)) -> 3.5885167 | D10: =IF((D5-D7)<=0,"never",Inputs!$D$10/(D5-D7)) -> 0.71647902 | E10: advisor day cost ÷ contribution before advisor cost
A11: Contribution per customer per year | B11: =Inputs!$B$16*B8+Inputs!$B$17*(Inputs!$B$18*(Inputs!$B$8-Inputs!$B$9)-Inputs!$B$19) -> -1512.9667 | C11: =Inputs!$C$16*C8+Inputs!$C$17*(Inputs!$C$18*(Inputs!$C$8-Inputs!$C$9)-Inputs!$C$19) -> 1719 | D11: =Inputs!$D$16*D8+Inputs!$D$17*(Inputs!$D$18*(Inputs!$D$8-Inputs!$D$9)-Inputs!$D$19) -> 11316 | E11: visits × contribution + app reorders × (value × net margin − fulfilment)
A12: Share of yearly contribution from app reorders | B12: =IF(B11=0,0,1-Inputs!$B$16*B8/B11) -> -0.12690299 | C12: =IF(C11=0,0,1-Inputs!$C$16*C8/C11) -> 0.92495637 | D12: =IF(D11=0,0,1-Inputs!$D$16*D8/D11) -> 0.40827147 | E12: 1 − visit contribution ÷ total
A13: CAC payback (months) | B13: =IF(B11<=0,"never",Inputs!$B$15/(B11/12)) -> never | C13: =IF(C11<=0,"never",Inputs!$C$15/(C11/12)) -> 6.9808028 | D13: =IF(D11<=0,"never",Inputs!$D$15/(D11/12)) -> 0.74231177 | E13: CAC ÷ monthly contribution per customer
A14: Contribution-to-CAC ratio (year 1) | B14: =IF(Inputs!$B$15=0,0,B11/Inputs!$B$15) -> -1.0086444 | C14: =IF(Inputs!$C$15=0,0,C11/Inputs!$C$15) -> 1.719 | D14: =IF(Inputs!$D$15=0,0,D11/Inputs!$D$15) -> 16.165714 | E14: year-1 contribution ÷ CAC
A17: Bear, Base and Bull columns each use their own inputs. Cover uses the selected scenario on Inputs!B22.

Sheet Sensitivity
A1: Sensitivity: contribution per visit (₹), base case, other inputs held
A3: Visit conversion ↓ × visits per advisor per day →
B4: 2 | C4: 3 | D4: 4 | E4: 5 | F4: 6
A5: 0.4 | B5: =$A5*Inputs!$C$6*Inputs!$C$7*(Inputs!$C$8-Inputs!$C$9)-Inputs!$C$10/B$4-(Inputs!$C$12+Inputs!$C$13+Inputs!$C$14) -> -618 | C5: =$A5*Inputs!$C$6*Inputs!$C$7*(Inputs!$C$8-Inputs!$C$9)-Inputs!$C$10/C$4-(Inputs!$C$12+Inputs!$C$13+Inputs!$C$14) -> -368 | D5: =$A5*Inputs!$C$6*Inputs!$C$7*(Inputs!$C$8-Inputs!$C$9)-Inputs!$C$10/D$4-(Inputs!$C$12+Inputs!$C$13+Inputs!$C$14) -> -243 | E5: =$A5*Inputs!$C$6*Inputs!$C$7*(Inputs!$C$8-Inputs!$C$9)-Inputs!$C$10/E$4-(Inputs!$C$12+Inputs!$C$13+Inputs!$C$14) -> -168 | F5: =$A5*Inputs!$C$6*Inputs!$C$7*(Inputs!$C$8-Inputs!$C$9)-Inputs!$C$10/F$4-(Inputs!$C$12+Inputs!$C$13+Inputs!$C$14) -> -118
A6: 0.5 | B6: =$A6*Inputs!$C$6*Inputs!$C$7*(Inputs!$C$8-Inputs!$C$9)-Inputs!$C$10/B$4-(Inputs!$C$12+Inputs!$C$13+Inputs!$C$14) -> -475 | C6: =$A6*Inputs!$C$6*Inputs!$C$7*(Inputs!$C$8-Inputs!$C$9)-Inputs!$C$10/C$4-(Inputs!$C$12+Inputs!$C$13+Inputs!$C$14) -> -225 | D6: =$A6*Inputs!$C$6*Inputs!$C$7*(Inputs!$C$8-Inputs!$C$9)-Inputs!$C$10/D$4-(Inputs!$C$12+Inputs!$C$13+Inputs!$C$14) -> -100 | E6: =$A6*Inputs!$C$6*Inputs!$C$7*(Inputs!$C$8-Inputs!$C$9)-Inputs!$C$10/E$4-(Inputs!$C$12+Inputs!$C$13+Inputs!$C$14) -> -25 | F6: =$A6*Inputs!$C$6*Inputs!$C$7*(Inputs!$C$8-Inputs!$C$9)-Inputs!$C$10/F$4-(Inputs!$C$12+Inputs!$C$13+Inputs!$C$14) -> 25
A7: 0.6 | B7: =$A7*Inputs!$C$6*Inputs!$C$7*(Inputs!$C$8-Inputs!$C$9)-Inputs!$C$10/B$4-(Inputs!$C$12+Inputs!$C$13+Inputs!$C$14) -> -332 | C7: =$A7*Inputs!$C$6*Inputs!$C$7*(Inputs!$C$8-Inputs!$C$9)-Inputs!$C$10/C$4-(Inputs!$C$12+Inputs!$C$13+Inputs!$C$14) -> -82 | D7: =$A7*Inputs!$C$6*Inputs!$C$7*(Inputs!$C$8-Inputs!$C$9)-Inputs!$C$10/D$4-(Inputs!$C$12+Inputs!$C$13+Inputs!$C$14) -> 43 | E7: =$A7*Inputs!$C$6*Inputs!$C$7*(Inputs!$C$8-Inputs!$C$9)-Inputs!$C$10/E$4-(Inputs!$C$12+Inputs!$C$13+Inputs!$C$14) -> 118 | F7: =$A7*Inputs!$C$6*Inputs!$C$7*(Inputs!$C$8-Inputs!$C$9)-Inputs!$C$10/F$4-(Inputs!$C$12+Inputs!$C$13+Inputs!$C$14) -> 168
A8: 0.7 | B8: =$A8*Inputs!$C$6*Inputs!$C$7*(Inputs!$C$8-Inputs!$C$9)-Inputs!$C$10/B$4-(Inputs!$C$12+Inputs!$C$13+Inputs!$C$14) -> -189 | C8: =$A8*Inputs!$C$6*Inputs!$C$7*(Inputs!$C$8-Inputs!$C$9)-Inputs!$C$10/C$4-(Inputs!$C$12+Inputs!$C$13+Inputs!$C$14) -> 61 | D8: =$A8*Inputs!$C$6*Inputs!$C$7*(Inputs!$C$8-Inputs!$C$9)-Inputs!$C$10/D$4-(Inputs!$C$12+Inputs!$C$13+Inputs!$C$14) -> 186 | E8: =$A8*Inputs!$C$6*Inputs!$C$7*(Inputs!$C$8-Inputs!$C$9)-Inputs!$C$10/E$4-(Inputs!$C$12+Inputs!$C$13+Inputs!$C$14) -> 261 | F8: =$A8*Inputs!$C$6*Inputs!$C$7*(Inputs!$C$8-Inputs!$C$9)-Inputs!$C$10/F$4-(Inputs!$C$12+Inputs!$C$13+Inputs!$C$14) -> 311
A9: 0.8 | B9: =$A9*Inputs!$C$6*Inputs!$C$7*(Inputs!$C$8-Inputs!$C$9)-Inputs!$C$10/B$4-(Inputs!$C$12+Inputs!$C$13+Inputs!$C$14) -> -46 | C9: =$A9*Inputs!$C$6*Inputs!$C$7*(Inputs!$C$8-Inputs!$C$9)-Inputs!$C$10/C$4-(Inputs!$C$12+Inputs!$C$13+Inputs!$C$14) -> 204 | D9: =$A9*Inputs!$C$6*Inputs!$C$7*(Inputs!$C$8-Inputs!$C$9)-Inputs!$C$10/D$4-(Inputs!$C$12+Inputs!$C$13+Inputs!$C$14) -> 329 | E9: =$A9*Inputs!$C$6*Inputs!$C$7*(Inputs!$C$8-Inputs!$C$9)-Inputs!$C$10/E$4-(Inputs!$C$12+Inputs!$C$13+Inputs!$C$14) -> 404 | F9: =$A9*Inputs!$C$6*Inputs!$C$7*(Inputs!$C$8-Inputs!$C$9)-Inputs!$C$10/F$4-(Inputs!$C$12+Inputs!$C$13+Inputs!$C$14) -> 454
A12: Average selling price ↓ × items per converting visit →
B13: 1.5 | C13: 2 | D13: 2.5 | E13: 3 | F13: 3.5
A14: 1500 | B14: =Inputs!$C$5*B$13*$A14*(Inputs!$C$8-Inputs!$C$9)-Inputs!$C$10/Inputs!$C$11-(Inputs!$C$12+Inputs!$C$13+Inputs!$C$14) -> -464 | C14: =Inputs!$C$5*C$13*$A14*(Inputs!$C$8-Inputs!$C$9)-Inputs!$C$10/Inputs!$C$11-(Inputs!$C$12+Inputs!$C$13+Inputs!$C$14) -> -347 | D14: =Inputs!$C$5*D$13*$A14*(Inputs!$C$8-Inputs!$C$9)-Inputs!$C$10/Inputs!$C$11-(Inputs!$C$12+Inputs!$C$13+Inputs!$C$14) -> -230 | E14: =Inputs!$C$5*E$13*$A14*(Inputs!$C$8-Inputs!$C$9)-Inputs!$C$10/Inputs!$C$11-(Inputs!$C$12+Inputs!$C$13+Inputs!$C$14) -> -113 | F14: =Inputs!$C$5*F$13*$A14*(Inputs!$C$8-Inputs!$C$9)-Inputs!$C$10/Inputs!$C$11-(Inputs!$C$12+Inputs!$C$13+Inputs!$C$14) -> 4
A15: 2000 | B15: =Inputs!$C$5*B$13*$A15*(Inputs!$C$8-Inputs!$C$9)-Inputs!$C$10/Inputs!$C$11-(Inputs!$C$12+Inputs!$C$13+Inputs!$C$14) -> -347 | C15: =Inputs!$C$5*C$13*$A15*(Inputs!$C$8-Inputs!$C$9)-Inputs!$C$10/Inputs!$C$11-(Inputs!$C$12+Inputs!$C$13+Inputs!$C$14) -> -191 | D15: =Inputs!$C$5*D$13*$A15*(Inputs!$C$8-Inputs!$C$9)-Inputs!$C$10/Inputs!$C$11-(Inputs!$C$12+Inputs!$C$13+Inputs!$C$14) -> -35 | E15: =Inputs!$C$5*E$13*$A15*(Inputs!$C$8-Inputs!$C$9)-Inputs!$C$10/Inputs!$C$11-(Inputs!$C$12+Inputs!$C$13+Inputs!$C$14) -> 121 | F15: =Inputs!$C$5*F$13*$A15*(Inputs!$C$8-Inputs!$C$9)-Inputs!$C$10/Inputs!$C$11-(Inputs!$C$12+Inputs!$C$13+Inputs!$C$14) -> 277
A16: 2500 | B16: =Inputs!$C$5*B$13*$A16*(Inputs!$C$8-Inputs!$C$9)-Inputs!$C$10/Inputs!$C$11-(Inputs!$C$12+Inputs!$C$13+Inputs!$C$14) -> -230 | C16: =Inputs!$C$5*C$13*$A16*(Inputs!$C$8-Inputs!$C$9)-Inputs!$C$10/Inputs!$C$11-(Inputs!$C$12+Inputs!$C$13+Inputs!$C$14) -> -35 | D16: =Inputs!$C$5*D$13*$A16*(Inputs!$C$8-Inputs!$C$9)-Inputs!$C$10/Inputs!$C$11-(Inputs!$C$12+Inputs!$C$13+Inputs!$C$14) -> 160 | E16: =Inputs!$C$5*E$13*$A16*(Inputs!$C$8-Inputs!$C$9)-Inputs!$C$10/Inputs!$C$11-(Inputs!$C$12+Inputs!$C$13+Inputs!$C$14) -> 355 | F16: =Inputs!$C$5*F$13*$A16*(Inputs!$C$8-Inputs!$C$9)-Inputs!$C$10/Inputs!$C$11-(Inputs!$C$12+Inputs!$C$13+Inputs!$C$14) -> 550
A17: 3000 | B17: =Inputs!$C$5*B$13*$A17*(Inputs!$C$8-Inputs!$C$9)-Inputs!$C$10/Inputs!$C$11-(Inputs!$C$12+Inputs!$C$13+Inputs!$C$14) -> -113 | C17: =Inputs!$C$5*C$13*$A17*(Inputs!$C$8-Inputs!$C$9)-Inputs!$C$10/Inputs!$C$11-(Inputs!$C$12+Inputs!$C$13+Inputs!$C$14) -> 121 | D17: =Inputs!$C$5*D$13*$A17*(Inputs!$C$8-Inputs!$C$9)-Inputs!$C$10/Inputs!$C$11-(Inputs!$C$12+Inputs!$C$13+Inputs!$C$14) -> 355 | E17: =Inputs!$C$5*E$13*$A17*(Inputs!$C$8-Inputs!$C$9)-Inputs!$C$10/Inputs!$C$11-(Inputs!$C$12+Inputs!$C$13+Inputs!$C$14) -> 589 | F17: =Inputs!$C$5*F$13*$A17*(Inputs!$C$8-Inputs!$C$9)-Inputs!$C$10/Inputs!$C$11-(Inputs!$C$12+Inputs!$C$13+Inputs!$C$14) -> 823
A18: 3500 | B18: =Inputs!$C$5*B$13*$A18*(Inputs!$C$8-Inputs!$C$9)-Inputs!$C$10/Inputs!$C$11-(Inputs!$C$12+Inputs!$C$13+Inputs!$C$14) -> 4 | C18: =Inputs!$C$5*C$13*$A18*(Inputs!$C$8-Inputs!$C$9)-Inputs!$C$10/Inputs!$C$11-(Inputs!$C$12+Inputs!$C$13+Inputs!$C$14) -> 277 | D18: =Inputs!$C$5*D$13*$A18*(Inputs!$C$8-Inputs!$C$9)-Inputs!$C$10/Inputs!$C$11-(Inputs!$C$12+Inputs!$C$13+Inputs!$C$14) -> 550 | E18: =Inputs!$C$5*E$13*$A18*(Inputs!$C$8-Inputs!$C$9)-Inputs!$C$10/Inputs!$C$11-(Inputs!$C$12+Inputs!$C$13+Inputs!$C$14) -> 823 | F18: =Inputs!$C$5*F$13*$A18*(Inputs!$C$8-Inputs!$C$9)-Inputs!$C$10/Inputs!$C$11-(Inputs!$C$12+Inputs!$C$13+Inputs!$C$14) -> 1096
